{"佩奇线报": {"作者": "佩奇线报", "发布时间": "2024-05-19 13:02:45", "发布ip": "来自江西", "点赞数量": "113", "评论内容": "每次都能猜对但是每次都跑马的来集合"}, "朝阳区56号佳丽": {"作者": "朝阳区56号佳丽", "发布时间": "2024-05-19 13:03:09", "发布ip": "来自浙江", "点赞数量": "41", "评论内容": "一直参与，一直知道口令，一直跑马"}, "半勺小奶鹿": {"作者": "半勺小奶鹿", "发布时间": "2024-05-19 13:16:48", "发布ip": "来自广东", "点赞数量": "25", "评论内容": "每次都跑马的来集合，能不能弄一下___"}, "阿琰甜的很正经": {"作者": "阿琰甜的很正经", "发布时间": "2024-05-19 13:53:16", "发布ip": "来自河南", "点赞数量": "17", "评论内容": "四家店明明有原料就是不上架 有的店等早上开门或者晚上8点上线半个小时立刻下线 不让用可以直接不送的______虽然理解怕爆单 但不至于找人最少的时间段就偷偷上线半个小时吧"}, "Oo熊叮叮叮叮叮o": {"作者": "Oo熊叮叮叮叮叮o", "发布时间": "2024-05-19 13:29:48", "发布ip": "来自广西", "点赞数量": "17", "评论内容": "这么多店都没有原料，有券都不能用，这个问题你们怎么解决___"}, "星期五出门": {"作者": "星期五出门", "发布时间": "2024-05-19 14:11:53", "发布ip": "来自湖南", "点赞数量": "7", "评论内容": "门店都停止接单了___"}, "見呸菊个": {"作者": "見呸菊个", "发布时间": "2024-05-19 13:05:43", "发布ip": "来自浙江", "点赞数量": "2", "评论内容": "这谁能想得到___"}, "IDT54014": {"作者": "IDT54014", "发布时间": "2024-05-19 13:46:45", "发布ip": "来自江苏", "点赞数量": "9", "评论内容": "小程序都爆了根本点不了单，用不了券，我请问呢，不会25号之后小程序就维修好了吧"}, "阳光倾城少年": {"作者": "阳光倾城少年", "发布时间": "2024-05-19 13:13:19", "发布ip": "来自四川", "点赞数量": "1", "评论内容": "第一次___"}, "那就在这个夏天和我一起看海叭": {"作者": "那就在这个夏天和我一起看海叭", "发布时间": "2024-05-19 13:05:05", "发布ip": "来自广东", "点赞数量": "1", "评论内容": "一直跑🐴？___"}, "悲伤的草莓大福": {"作者": "悲伤的草莓大福", "发布时间": "2024-05-19 13:09:39", "发布ip": "来自重庆", "点赞数量": "2", "评论内容": "猜对啦___"}, "月亮和六便士都会有的": {"作者": "月亮和六便士都会有的", "发布时间": "2024-05-19 13:07:32", "发布ip": "来自贵州", "点赞数量": "1", "评论内容": "一直在跑马"}, "窝窝小李莉168": {"作者": "窝窝小李莉168", "发布时间": "2024-05-19 13:04:34", "发布ip": "来自广东", "点赞数量": "1", "评论内容": "参加几天了，一次都没得"}, "舟舟想喝粥粥": {"作者": "舟舟想喝粥粥", "发布时间": "2024-05-19 23:12:31", "发布ip": "来自湖北", "点赞数量": "0", "评论内容": "抢不到哇"}, "小吴有福气": {"作者": "小吴有福气", "发布时间": "2024-05-19 21:21:44", "发布ip": "来自河南", "点赞数量": "0", "评论内容": "今天猜错了"}, "矫情的大脸猫_": {"作者": "矫情的大脸猫_", "发布时间": "2024-05-19 18:47:29", "发布ip": "来自云南", "点赞数量": "0", "评论内容": "跑马跑的我心累___"}, "夏天超热的呢": {"作者": "夏天超热的呢", "发布时间": "2024-05-19 18:38:24", "发布ip": "来自广东", "点赞数量": "0", "评论内容": "姬姐小程序又崩了______我要喝奶茶______"}, "为橘子准备四季": {"作者": "为橘子准备四季", "发布时间": "2024-05-19 16:13:11", "发布ip": "来自浙江", "点赞数量": "0", "评论内容": "新品挺好喝的___"}, "海水有尽头c": {"作者": "海水有尽头c", "发布时间": "2024-05-19 14:50:02", "发布ip": "来自广东", "点赞数量": "1", "评论内容": "建议直接送我___"}, "-FunYANG": {"作者": "-FunYANG", "发布时间": "2024-05-19 14:28:41", "发布ip": "来自上海", "点赞数量": "1", "评论内容": "好喝______比伯牙好喝___"}}